{
    "base": "/t/acimoe/workbook/l020/",
    "time": [
        {
            "id": "p0",
            "seconds": 0
        },
        {
            "id": "p1",
            "seconds": 9.345587
        },
        {
            "id": "p2",
            "seconds": 62.995096
        },
        {
            "id": "p3",
            "seconds": 106.234224
        },
        {
            "id": "p4",
            "seconds": 157.22603
        },
        {
            "id": "p5",
            "seconds": 189.047573
        }
    ]
}
