{
    "base": "/t/acimoe/workbook/l083/",
    "time": [
        {
            "id": "p0",
            "seconds": 0
        },
        {
            "id": "p1",
            "seconds": 2.406387
        },
        {
            "id": "p2",
            "seconds": 9.65736
        },
        {
            "id": "p3",
            "seconds": 56.415733
        },
        {
            "id": "p4",
            "seconds": 65.664225
        },
        {
            "id": "p5",
            "seconds": 100.41081
        },
        {
            "id": "p6",
            "seconds": 124.667511
        },
        {
            "id": "p7",
            "seconds": 157.90986
        },
        {
            "id": "p8",
            "seconds": 168.165162
        }
    ]
}
