{
    "base": "/t/acimoe/workbook/l125/",
    "time": [
        {
            "id": "p0",
            "seconds": 0
        },
        {
            "id": "p1",
            "seconds": 10.669688
        },
        {
            "id": "p2",
            "seconds": 48.92102
        },
        {
            "id": "p3",
            "seconds": 86.92859
        },
        {
            "id": "p4",
            "seconds": 127.427919
        },
        {
            "id": "p5",
            "seconds": 159.668212
        },
        {
            "id": "p6",
            "seconds": 194.418498
        },
        {
            "id": "p7",
            "seconds": 229.922365
        },
        {
            "id": "p8",
            "seconds": 264.91488
        },
        {
            "id": "p9",
            "seconds": 298.66501
        },
        {
            "id": "p10",
            "seconds": 333.16985
        }
    ]
}
