{
    "base": "/t/acimoe/workbook/review6/",
    "time": [
        {
            "id": "p0",
            "seconds": 0
        },
        {
            "id": "p1",
            "seconds": 4.900903
        },
        {
            "id": "p2",
            "seconds": 55.404255
        },
        {
            "id": "p3",
            "seconds": 104.664305
        },
        {
            "id": "p4",
            "seconds": 121.416273
        },
        {
            "id": "p5",
            "seconds": 131.666173
        },
        {
            "id": "p6",
            "seconds": 170.655525
        },
        {
            "id": "p7",
            "seconds": 209.155074
        },
        {
            "id": "p8",
            "seconds": 241.662658
        },
        {
            "id": "p9",
            "seconds": 250.161286
        },
        {
            "id": "p10",
            "seconds": 257.906632
        },
        {
            "id": "p11",
            "seconds": 291.658757
        }
    ]
}
